textflowsms/__init__.py
textflowsms-0.1.0.dist-info/METADATA
textflowsms-0.1.0.dist-info/WHEEL
textflowsms-0.1.0.dist-info/licenses/LICENSE
textflowsms-0.1.0.dist-info/RECORD
