Metadata-Version: 2.1
Name: textflowsms
Version: 0.1.0
Summary: Python library that helps you send SMS using TextFlow API
Author-email: TextFlow <admin@textflow.me>
License-Expression: MIT
License-File: LICENSE
Keywords: api,api-client,simple-sms,sms,sms-api,sms-verification,text-message,user-verification
Classifier: License :: OSI Approved :: MIT License
Classifier: Operating System :: OS Independent
Classifier: Programming Language :: Python :: 3.6
Classifier: Programming Language :: Python :: 3.7
Classifier: Programming Language :: Python :: 3.8
Classifier: Programming Language :: Python :: 3.9
Classifier: Programming Language :: Python :: 3.10
Classifier: Programming Language :: Python :: 3.11
Requires-Python: >=3.6
Requires-Dist: requests
